[{"date": "2019-11-11 11:11:11", "type": "type1", "user": "user1", "module": "module1", "param": "param1"}, {"date": "2022-11-07 15:59:44", "type": "error", "user": null, "module": "main", "param": "Expecting value: line 1 column 1 (char 0)"}, {"date": "2022-11-07 16:00:14", "type": "error", "user": null, "module": "main", "param": "Ошибка в start_window"}, {"date": "2022-11-07 16:01:26", "type": "error", "user": null, "module": "main", "param": "Неверный логин или пароль"}, {"date": "2022-11-07 16:01:30", "type": "error", "user": null, "module": "main", "param": "Неверный логин или пароль"}, {"date": "2022-11-07 16:01:57", "type": "error", "user": null, "module": "main", "param": "save_db() missing 1 required positional argument: 'db'"}, {"date": "2022-11-07 16:02:02", "type": "error", "user": null, "module": "main", "param": "Ошибка в start_window"}, {"date": "2022-11-07 16:02:18", "type": "error", "user": null, "module": "main", "param": "Ошибка в start_window"}, {"date": "2022-11-07 16:02:26", "type": "error", "user": null, "module": "main", "param": "save_db() missing 1 required positional argument: 'db'"}, {"date": "2022-11-07 16:02:34", "type": "error", "user": null, "module": "main", "param": "Ошибка в start_window"}, {"date": "2022-11-07 16:04:18", "type": "error", "user": null, "module": "main", "param": "Неверный логин или пароль"}, {"date": "2022-11-07 16:04:34", "type": "error", "user": "UID:1", "module": "main", "param": "Ошибка в main_menu_window"}, {"date": "2022-11-07 16:04:36", "type": "error", "user": null, "module": "main", "param": "local variable 'person' referenced before assignment"}, {"date": "2022-11-07 16:04:54", "type": "error", "user": "UID:2", "module": "main", "param": "Ошибка в main_menu_window"}, {"date": "2022-11-07 16:04:55", "type": "error", "user": null, "module": "main", "param": "local variable 'person' referenced before assignment"}, {"date": "2022-11-07 16:05:06", "type": "error", "user": null, "module": "main", "param": "Ошибка в start_window"}, {"date": "2022-11-07 16:05:07", "type": "error", "user": null, "module": "main", "param": "Ошибка в start_window"}, {"date": "2022-11-07 16:05:08", "type": "error", "user": null, "module": "main", "param": "Ошибка в start_window"}, {"date": "2022-11-07 16:05:08", "type": "error", "user": null, "module": "main", "param": "Ошибка в start_window"}, {"date": "2022-11-07 16:05:09", "type": "error", "user": null, "module": "main", "param": "Ошибка в start_window"}, {"date": "2022-11-07 16:05:09", "type": "error", "user": null, "module": "main", "param": "Ошибка в start_window"}, {"date": "2022-11-07 16:05:10", "type": "error", "user": null, "module": "main", "param": "Ошибка в start_window"}, {"date": "2022-11-07 16:05:13", "type": "error", "user": null, "module": "main", "param": "Ошибка в start_window"}, {"date": "2022-11-07 16:05:17", "type": "error", "user": null, "module": "main", "param": "Ошибка в start_window"}, {"date": "2022-11-07 16:10:13", "type": "error", "user": null, "module": "main", "param": "local variable 'msg' referenced before assignment"}, {"date": "2022-11-07 16:11:13", "type": "error", "user": null, "module": "main", "param": "can only concatenate str (not \"NoneType\") to str"}, {"date": "2022-11-07 16:13:00", "type": "error", "user": null, "module": "main", "param": "can only concatenate str (not \"NoneType\") to str"}, {"date": "2022-11-07 16:14:59", "type": "error", "user": null, "module": "main", "param": "Ошибка в start_window"}, {"date": "2022-11-07 16:15:20", "type": "error", "user": null, "module": "main", "param": "Такой логин уже существует"}, {"date": "2022-11-07 16:15:31", "type": "error", "user": null, "module": "main", "param": "Такой логин уже существует"}, {"date": "2022-11-07 16:15:46", "type": "error", "user": "UID:3", "module": "main", "param": "Ошибка в main_menu_window"}, {"date": "2022-11-07 16:15:47", "type": "error", "user": null, "module": "main", "param": "local variable 'person' referenced before assignment"}, {"date": "2022-11-07 16:16:01", "type": "error", "user": null, "module": "main", "param": "Ошибка в start_window"}, {"date": "2022-11-07 16:16:03", "type": "error", "user": null, "module": "main", "param": "Ошибка в start_window"}, {"date": "2022-11-07 16:16:52", "type": "error", "user": null, "module": "main", "param": "Такой логин уже существует"}, {"date": "2022-11-07 16:17:28", "type": "error", "user": null, "module": "main", "param": "Такой логин уже существует"}, {"date": "2022-11-07 16:17:39", "type": "error", "user": "UID:1", "module": "main", "param": "Ошибка в main_menu_window"}, {"date": "2022-11-07 16:17:40", "type": "error", "user": null, "module": "main", "param": "local variable 'person' referenced before assignment"}, {"date": "2022-11-07 16:17:46", "type": "error", "user": "UID:1", "module": "main", "param": "Ошибка в main_menu_window"}, {"date": "2022-11-07 16:17:47", "type": "error", "user": null, "module": "main", "param": "local variable 'person' referenced before assignment"}, {"date": "2022-11-07 16:17:53", "type": "error", "user": "UID:1", "module": "main", "param": "Ошибка в main_menu_window"}, {"date": "2022-11-07 16:17:57", "type": "error", "user": null, "module": "main", "param": "local variable 'person' referenced before assignment"}, {"date": "2022-11-07 16:19:34", "type": "error", "user": "UID:1", "module": "main", "param": "Ошибка в main_menu_window"}, {"date": "2022-11-07 16:19:36", "type": "error", "user": null, "module": "main", "param": "local variable 'person' referenced before assignment"}, {"date": "2022-11-07 16:19:38", "type": "error", "user": null, "module": "main", "param": "Ошибка в start_window"}, {"date": "2022-11-07 16:19:40", "type": "error", "user": null, "module": "main", "param": "Ошибка в start_window"}, {"date": "2022-11-07 16:19:42", "type": "error", "user": null, "module": "main", "param": "Ошибка в start_window"}, {"date": "2022-11-07 16:19:45", "type": "error", "user": null, "module": "main", "param": "Ошибка в start_window"}, {"date": "2022-11-07 16:21:05", "type": "error", "user": "UID:1", "module": "main", "param": "Ошибка в main_menu_window"}, {"date": "2022-11-07 16:21:06", "type": "error", "user": null, "module": "main", "param": "local variable 'person' referenced before assignment"}, {"date": "2022-11-07 16:21:32", "type": "error", "user": null, "module": "main", "param": "Ошибка в start_window. Выбрано: None"}, {"date": "2022-11-07 16:21:35", "type": "error", "user": null, "module": "main", "param": "Ошибка в start_window. Выбрано: None"}, {"date": "2022-11-07 16:32:20", "type": "error", "user": null, "module": "main", "param": "start_window() missing 1 required positional argument: 'session_id'"}, {"date": "2022-11-07 16:33:00", "type": "error", "user": null, "module": "main", "param": "main_menu_window() missing 1 required positional argument: 'session_id'"}, {"date": "2022-11-07 16:36:18", "type": "error", "user": "UID:1", "module": "main", "param": "Ошибка в main_menu_window"}, {"date": "2022-11-07 16:36:19", "type": "error", "user": null, "module": "main", "param": "local variable 'person' referenced before assignment"}, {"date": "2022-11-07 16:36:31", "type": "error", "user": null, "module": "main", "param": "Ошибка в start_window. Выбрано: None"}, {"date": "2022-11-07 16:36:42", "type": "error", "user": "UID:1", "module": "main", "param": "Ошибка в main_menu_window"}, {"date": "2022-11-07 16:36:49", "type": "error", "user": null, "module": "main", "param": "local variable 'person' referenced before assignment"}, {"date": "2022-11-07 16:36:52", "type": "error", "user": null, "module": "main", "param": "Ошибка в start_window. Выбрано: None"}, {"date": "2022-11-07 16:48:34", "type": "error", "user": "UID:1", "module": "main", "param": "Ошибка в main_menu_window"}, {"date": "2022-11-07 16:48:37", "type": "error", "user": null, "module": "main", "param": "'int' object has no attribute 'strip'"}, {"date": "2022-11-07 16:49:54", "type": "error", "user": "UID:1", "module": "main", "param": "Ошибка в main_menu_window"}, {"date": "2022-11-07 16:49:56", "type": "error", "user": null, "module": "main", "param": "'NoneType' object is not iterable"}, {"date": "2022-11-07 16:49:56", "type": "viewed", "user": "UID:1", "module": "main", "param": ""}, {"date": "2022-11-07 16:50:00", "type": "error", "user": "UID:1", "module": "main", "param": "Ошибка в main_menu_window"}, {"date": "2022-11-07 16:50:01", "type": "error", "user": null, "module": "main", "param": "'NoneType' object is not iterable"}, {"date": "2022-11-07 16:50:01", "type": "viewed", "user": "UID:1", "module": "main", "param": ""}, {"date": "2022-11-07 16:50:07", "type": "error", "user": null, "module": "main", "param": "'NoneType' object is not iterable"}, {"date": "2022-11-07 16:50:07", "type": "viewed", "user": "UID:1", "module": "main", "param": ""}, {"date": "2022-11-07 16:50:10", "type": "error", "user": null, "module": "main", "param": "'NoneType' object is not iterable"}, {"date": "2022-11-07 16:50:10", "type": "viewed", "user": "UID:1", "module": "main", "param": ""}, {"date": "2022-11-07 16:50:13", "type": "error", "user": null, "module": "main", "param": "'NoneType' object is not iterable"}, {"date": "2022-11-07 16:50:13", "type": "viewed", "user": "UID:1", "module": "main", "param": ""}, {"date": "2022-11-07 16:50:16", "type": "error", "user": null, "module": "main", "param": "'NoneType' object is not iterable"}, {"date": "2022-11-07 16:50:16", "type": "viewed", "user": "UID:1", "module": "main", "param": ""}, {"date": "2022-11-07 19:02:20", "type": "error", "user": "UID:1", "module": "main", "param": "Ошибка в main_menu_window"}, {"date": "2022-11-07 19:02:21", "type": "error", "user": null, "module": "main", "param": "'NoneType' object is not iterable"}, {"date": "2022-11-07 19:02:21", "type": "viewed", "user": "UID:1", "module": "main", "param": ""}, {"date": "2022-11-07 19:04:12", "type": "error", "user": "UID:1", "module": "main", "param": "Ошибка в main_menu_window"}, {"date": "2022-11-07 19:04:13", "type": "error", "user": null, "module": "main", "param": "'NoneType' object is not iterable"}, {"date": "2022-11-07 19:04:13", "type": "viewed", "user": "UID:1", "module": "main", "param": ""}, {"date": "2022-11-07 19:06:05", "type": "error", "user": "UID:1", "module": "main", "param": "Ошибка в main_menu_window"}, {"date": "2022-11-07 19:06:06", "type": "error", "user": null, "module": "main", "param": "'NoneType' object is not iterable"}, {"date": "2022-11-07 19:06:06", "type": "viewed", "user": "UID:1", "module": "main", "param": ""}, {"date": "2022-11-07 19:06:20", "type": "error", "user": null, "module": "main", "param": "Ошибка в start_window. Выбрано: None"}, {"date": "2022-11-07 19:06:22", "type": "error", "user": null, "module": "main", "param": "Ошибка в start_window. Выбрано: None"}, {"date": "2022-11-07 19:06:23", "type": "error", "user": null, "module": "main", "param": "Ошибка в start_window. Выбрано: None"}, {"date": "2022-11-07 19:06:24", "type": "error", "user": null, "module": "main", "param": "Ошибка в start_window. Выбрано: None"}, {"date": "2022-11-07 19:10:44", "type": "error", "user": "UID:1", "module": "main", "param": "Ошибка в main_menu_window"}, {"date": "2022-11-07 19:10:45", "type": "error", "user": "UID:1", "module": "main", "param": "'NoneType' object is not iterable"}, {"date": "2022-11-07 19:10:45", "type": "viewed", "user": "UID:1", "module": "main", "param": ""}, {"date": "2022-11-07 19:10:48", "type": "error", "user": null, "module": "main", "param": "Ошибка в start_window. Выбрано: None"}, {"date": "2022-11-07 19:11:44", "type": "error", "user": "UID:1", "module": "main", "param": "Ошибка в main_menu_window"}, {"date": "2022-11-07 19:11:47", "type": "error", "user": "UID:1", "module": "main", "param": "'NoneType' object is not iterable"}, {"date": "2022-11-07 19:11:47", "type": "viewed", "user": "UID:1", "module": "main", "param": ""}, {"date": "2022-11-07 19:15:42", "type": "error", "user": "UID:1", "module": "main", "param": "Ошибка в main_menu_window"}, {"date": "2022-11-07 19:15:44", "type": "error", "user": "UID:1", "module": "main", "param": "'NoneType' object is not iterable"}, {"date": "2022-11-07 19:15:44", "type": "viewed", "user": "UID:1", "module": "main", "param": ""}, {"date": "2022-11-07 19:16:24", "type": "error", "user": "UID:1", "module": "main", "param": "Ошибка в main_menu_window"}, {"date": "2022-11-07 19:16:25", "type": "error", "user": "UID:1", "module": "main", "param": "'NoneType' object is not iterable"}, {"date": "2022-11-07 19:16:25", "type": "viewed", "user": "UID:1", "module": "main", "param": ""}, {"date": "2022-11-07 19:19:56", "type": "error", "user": "UID:1", "module": "main", "param": "Ошибка в main_menu_window"}, {"date": "2022-11-07 19:19:57", "type": "error", "user": "UID:1", "module": "main", "param": "'NoneType' object is not iterable"}, {"date": "2022-11-07 19:19:57", "type": "viewed", "user": "UID:1", "module": "main", "param": ""}, {"date": "2022-11-07 19:21:07", "type": "error", "user": "UID:1", "module": "main", "param": "Ошибка в main_menu_window"}, {"date": "2022-11-07 19:21:09", "type": "error", "user": "UID:1", "module": "main", "param": "'NoneType' object is not iterable"}, {"date": "2022-11-07 19:21:09", "type": "viewed", "user": "UID:1", "module": "main", "param": ""}, {"date": "2022-11-07 19:38:47", "type": "error", "user": "UID:1", "module": "main", "param": "Ошибка в main_menu_window"}, {"date": "2022-11-07 19:38:49", "type": "error", "user": "UID:1", "module": "main", "param": "'NoneType' object is not iterable"}, {"date": "2022-11-07 19:38:49", "type": "viewed", "user": "UID:1", "module": "main", "param": ""}, {"date": "2022-11-07 19:39:30", "type": "error", "user": "UID:1", "module": "main", "param": "Ошибка в main_menu_window"}, {"date": "2022-11-07 19:39:30", "type": "error", "user": "UID:1", "module": "main", "param": "'NoneType' object is not iterable"}, {"date": "2022-11-07 19:39:30", "type": "viewed", "user": "UID:1", "module": "main", "param": ""}, {"date": "2022-11-07 19:40:32", "type": "error", "user": "UID:1", "module": "main", "param": "Ошибка в main_menu_window"}, {"date": "2022-11-07 19:40:34", "type": "error", "user": "UID:1", "module": "main", "param": "'NoneType' object is not iterable"}, {"date": "2022-11-07 19:40:34", "type": "viewed", "user": "UID:1", "module": "main", "param": ""}, {"date": "2022-11-07 19:41:31", "type": "error", "user": "UID:1", "module": "main", "param": "Ошибка в main_menu_window"}, {"date": "2022-11-07 19:41:40", "type": "error", "user": "UID:1", "module": "main", "param": "'NoneType' object is not iterable"}, {"date": "2022-11-07 19:41:40", "type": "viewed", "user": "UID:1", "module": "main", "param": ""}, {"date": "2022-11-07 19:43:40", "type": "viewed", "user": "UID:1", "module": "main", "param": "UID:3 ::: 333 333 333 333"}, {"date": "2022-11-07 19:43:54", "type": "error", "user": "UID:1", "module": "main", "param": "module 'log' has no attribute 'get_viewers'"}, {"date": "2022-11-07 19:44:05", "type": "error", "user": "UID:1", "module": "main", "param": "module 'log' has no attribute 'get_viewed'"}, {"date": "2022-11-07 20:14:38", "type": "viewed", "user": "UID:1", "module": "main", "param": "UID:1 ::: 111 111 111 111"}, {"date": "2022-11-07 20:53:50", "type": "error", "user": null, "module": "main", "param": "Неверный логин или пароль"}, {"date": "2022-11-07 20:54:07", "type": "error", "user": null, "module": "main", "param": "module 'log' has no attribute 'get_viewers'"}, {"date": "2022-11-07 20:54:21", "type": "error", "user": null, "module": "main", "param": "module 'log' has no attribute 'get_viewed'"}]